pgmuvi/__init__.py
pgmuvi/gps.py
pgmuvi/lightcurve.py
pgmuvi/test_script.py
pgmuvi/trainers.py
pgmuvi-0.1.0rc4.dist-info/LICENSE
pgmuvi-0.1.0rc4.dist-info/METADATA
pgmuvi-0.1.0rc4.dist-info/WHEEL
pgmuvi-0.1.0rc4.dist-info/top_level.txt
pgmuvi-0.1.0rc4.dist-info/RECORD
